mcdata/ManipularTabela.py
mcdata/__init__.py
mcdata/dicionarios.py
mcdata/s3.py
mcdata/transformar.py
mcdata_package-0.0.9.dist-info/LICENSE
mcdata_package-0.0.9.dist-info/METADATA
mcdata_package-0.0.9.dist-info/WHEEL
mcdata_package-0.0.9.dist-info/top_level.txt
mcdata_package-0.0.9.dist-info/RECORD
