Metadata-Version: 2.1
Name: mcdata-package
Version: 0.0.9
Summary: Pacote para facilitar o envio de arquivos para o s3, transformar arquivos csv e rds para Parquet, realizar limpeza simples dos dados e guardar dicionários de siglas governamentais.
Author: Rodrigo Martins
Author-email: rodrigo.martins@sou.inteli.edu.br
Classifier: Programming Language :: Python :: 3
Classifier: License :: OSI Approved :: MIT License
Classifier: Operating System :: OS Independent
Requires-Python: >=3.8
License-File: LICENSE
